{
  "name" : "Permissions",
  "comment" : null,
  "fullColumn" : [ {
    "name" : "id",
    "comment" : null,
    "type" : null,
    "shortType" : null,
    "custom" : false,
    "ext" : { }
  }, {
    "name" : "permissionsname",
    "comment" : null,
    "type" : null,
    "shortType" : null,
    "custom" : false,
    "ext" : { }
  } ],
  "pkColumn" : null,
  "otherColumn" : null,
  "savePackageName" : "com.zhang",
  "savePath" : "./springboot-vue-permission/src/main/java/com/zhang",
  "saveModelName" : "springboot-vue-permission"
}